Metadata-Version: 2.1
Name: legrandom
Version: 1.0
Summary: legacy random
Home-page: https://github.com/JezBurch1984/xrandom
Author: Example Author
Author-email: throwawayemail49572@gmail.com
License: UNKNOWN
Platform: UNKNOWN
Classifier: Programming Language :: Python :: 3
Classifier: License :: OSI Approved :: MIT License
Classifier: Operating System :: OS Independent
Requires-Python: >=3.6
